politico_civic_stump-0.1.0.dist-info/DESCRIPTION.rst
politico_civic_stump-0.1.0.dist-info/METADATA
politico_civic_stump-0.1.0.dist-info/RECORD
politico_civic_stump-0.1.0.dist-info/WHEEL
politico_civic_stump-0.1.0.dist-info/metadata.json
politico_civic_stump-0.1.0.dist-info/top_level.txt
stump/__init__.py
stump/apps.py
stump/celery.py
stump/conf.py
stump/fields.py
stump/pagination.py
stump/signals.py
stump/urls.py
stump/widgets.py
stump/admin/__init__.py
stump/admin/appearance.py
stump/migrations/0001_initial.py
stump/migrations/0002_auto_20180115_2219.py
stump/migrations/0003_auto_20180116_1912.py
stump/migrations/0004_auto_20180130_0203.py
stump/migrations/__init__.py
stump/models/__init__.py
stump/models/appearance.py
stump/models/appearance_type.py
stump/serializers/__init__.py
stump/serializers/appearance.py
stump/serializers/appearance_type.py
stump/tasks/__init__.py
stump/utils/__init__.py
stump/utils/importers.py
stump/viewsets/__init__.py
stump/viewsets/appearance.py
stump/viewsets/appearance_type.py
stump/viewsets/base.py
